suap_scraper/SUAP.py
suap_scraper/__init__.py
suap_scraper/config.py
suap_scraper/utils.py
suap_scraper-0.0.6.4.dist-info/LICENSE.md
suap_scraper-0.0.6.4.dist-info/METADATA
suap_scraper-0.0.6.4.dist-info/WHEEL
suap_scraper-0.0.6.4.dist-info/top_level.txt
suap_scraper-0.0.6.4.dist-info/RECORD
