Metadata-Version: 2.1
Name: suap-scraper
Version: 0.0.6.4
Summary: Um scraper para o SUAP do IFPB
Author-email: Jao42 <cavalcante.joao@protonmail.ch>
Project-URL: Homepage, https://github.com/Jao42/suap-scraper
Project-URL: Bug Tracker, https://github.com/Jao42/suap-scraper/issues
Classifier: Programming Language :: Python :: 3
Classifier: License :: OSI Approved :: MIT License
Classifier: Operating System :: OS Independent
Requires-Python: >=3.7
License-File: LICENSE.md
Requires-Dist: httpx
Requires-Dist: selectolax
